sparkline/__init__.py
sparkline/__main__.py
sparkline/sparkline.py
pysparklines-1.4.dist-info/LICENSE
pysparklines-1.4.dist-info/METADATA
pysparklines-1.4.dist-info/WHEEL
pysparklines-1.4.dist-info/entry_points.txt
pysparklines-1.4.dist-info/top_level.txt
pysparklines-1.4.dist-info/RECORD
