Metadata-Version: 2.1
Name: pysparklines
Version: 1.4
Summary: pysparklines is a unicode sparkline generation library.
Home-page: https://github.com/RedKrieg/pysparklines
Author: Brandon Whaley
Author-email: redkrieg@gmail.com
License: BSD 3-clause
Platform: any
Classifier: Development Status :: 5 - Production/Stable
Classifier: Environment :: Console
Classifier: Intended Audience :: Developers
Classifier: Intended Audience :: System Administrators
Classifier: License :: OSI Approved :: BSD License
Classifier: Operating System :: Unix
Classifier: Operating System :: POSIX
Classifier: Programming Language :: Python
Classifier: Programming Language :: Python :: 3 :: Only
Classifier: Topic :: Software Development
Classifier: Topic :: Software Development :: Libraries
Classifier: Topic :: Software Development :: Libraries :: Python Modules
Requires-Python: >=3.2
Provides-Extra: test
License-File: LICENSE
